jl_logger/__init__.py
jl_logger/_version.py
jl_logger/handlers.py
jl_logger/labextension/build_log.json
jl_logger/labextension/package.json
jl_logger/labextension/static/lib_index_js.b8a68a378639f9fa2095.js
jl_logger/labextension/static/lib_index_js.b8a68a378639f9fa2095.js.map
jl_logger/labextension/static/remoteEntry.c300492a70d3ca57bfc5.js
jl_logger/labextension/static/remoteEntry.c300492a70d3ca57bfc5.js.map
jl_logger/labextension/static/style.js
jl_logger/labextension/static/style_index_js.1ddf700d425d0d0d5c82.js
jl_logger/labextension/static/style_index_js.1ddf700d425d0d0d5c82.js.map
jl_logger/labextension/static/vendors-node_modules_css-loader_dist_runtime_api_js-node_modules_css-loader_dist_runtime_cssW-72eba1.675dddea69a670b77f2f.js
jl_logger/labextension/static/vendors-node_modules_css-loader_dist_runtime_api_js-node_modules_css-loader_dist_runtime_cssW-72eba1.675dddea69a670b77f2f.js.map
jl_logger-0.1.0.data/data/etc/jupyter/jupyter_notebook_config.d/jl_logger.json
jl_logger-0.1.0.data/data/etc/jupyter/jupyter_server_config.d/jl_logger.json
jl_logger-0.1.0.data/data/share/jupyter/labextensions/jl-logger/build_log.json
jl_logger-0.1.0.data/data/share/jupyter/labextensions/jl-logger/install.json
jl_logger-0.1.0.data/data/share/jupyter/labextensions/jl-logger/package.json
jl_logger-0.1.0.data/data/share/jupyter/labextensions/jl-logger/static/lib_index_js.b8a68a378639f9fa2095.js
jl_logger-0.1.0.data/data/share/jupyter/labextensions/jl-logger/static/lib_index_js.b8a68a378639f9fa2095.js.map
jl_logger-0.1.0.data/data/share/jupyter/labextensions/jl-logger/static/remoteEntry.c300492a70d3ca57bfc5.js
jl_logger-0.1.0.data/data/share/jupyter/labextensions/jl-logger/static/remoteEntry.c300492a70d3ca57bfc5.js.map
jl_logger-0.1.0.data/data/share/jupyter/labextensions/jl-logger/static/style.js
jl_logger-0.1.0.data/data/share/jupyter/labextensions/jl-logger/static/style_index_js.1ddf700d425d0d0d5c82.js
jl_logger-0.1.0.dist-info/LICENSE
jl_logger-0.1.0.dist-info/METADATA
jl_logger-0.1.0.dist-info/WHEEL
jl_logger-0.1.0.dist-info/top_level.txt
jl_logger-0.1.0.dist-info/RECORD
